{
  "version": "6",
  "dialect": "postgresql",
  "entries": [
    {
      "idx": 0,
      "version": "6",
      "when": 1716497682497,
      "tag": "0000_married_venus",
      "breakpoints": true
    },
    {
      "idx": 1,
      "version": "6",
      "when": 1716572670370,
      "tag": "0001_oval_captain_america",
      "breakpoints": true
    },
    {
      "idx": 2,
      "version": "6",
      "when": 1716574535881,
      "tag": "0002_charming_micromax",
      "breakpoints": true
    },
    {
      "idx": 3,
      "version": "6",
      "when": 1716582901402,
      "tag": "0003_wandering_landau",
      "breakpoints": true
    },
    {
      "idx": 4,
      "version": "6",
      "when": 1716583604567,
      "tag": "0004_bouncy_psylocke",
      "breakpoints": true
    },
    {
      "idx": 5,
      "version": "6",
      "when": 1716585295984,
      "tag": "0005_kind_steve_rogers",
      "breakpoints": true
    },
    {
      "idx": 6,
      "version": "6",
      "when": 1716599648220,
      "tag": "0006_clumsy_groot",
      "breakpoints": true
    }
  ]
}